{"id": "https://openalex.org/W2906483945", "doi": "https://doi.org/10.1109/vast.2017.8585658", "title": "CrystalBall: A Visual Analytic System for Future Event Discovery and Analysis from Social Media Data", "display_name": "CrystalBall: A Visual Analytic System for Future Event Discovery and Analysis from Social Media Data", "publication_year": 2017, "publication_date": "2017-10-01", "ids": {"openalex": "https://openalex.org/W2906483945", "doi": "https://doi.org/10.1109/vast.2017.8585658", "mag": "2906483945"}, "language": "en", "primary_location": {"id": "doi:10.1109/vast.2017.8585658", "is_oa": false, "landing_page_url": "https://doi.org/10.1109/vast.2017.8585658", "pdf_url": null, "source": null, "license": null, "license_id": null, "version": "publishedVersion", "is_accepted": true, "is_published": true, "raw_source_name": "2017 IEEE Conference on Visual Analytics Science and Technology (VAST)", "raw_type": "proceedings-article"}, "type": "article", "indexed_in": ["crossref"], "open_access": {"is_oa": false, "oa_status": "closed", "oa_url": null, "any_repository_has_fulltext": false}, "authorships": [{"author_position": "first", "author": {"id": "https://openalex.org/A5062185996", "display_name": "Isaac Cho", "orcid": "https://orcid.org/0000-0003-1582-8428"}, "institutions": [{"id": "https://openalex.org/I102149020", "display_name": "University of North Carolina at Charlotte", "ror": "https://ror.org/04dawnj30", "country_code": "US", "type": "education", "lineage": ["https://openalex.org/I102149020"]}], "countries": ["US"], "is_corresponding": false, "raw_author_name": "Isaac Cho", "raw_affiliation_strings": ["University of North Carolina at Charlotte"], "affiliations": [{"raw_affiliation_string": "University of North Carolina at Charlotte", "institution_ids": ["https://openalex.org/I102149020"]}]}, {"author_position": "middle", "author": {"id": "https://openalex.org/A5078317897", "display_name": "Ryan Wesslen", "orcid": "https://orcid.org/0000-0001-9638-8078"}, "institutions": [{"id": "https://openalex.org/I102149020", "display_name": "University of North Carolina at Charlotte", "ror": "https://ror.org/04dawnj30", "country_code": "US", "type": "education", "lineage": ["https://openalex.org/I102149020"]}], "countries": ["US"], "is_corresponding": false, "raw_author_name": "Ryan Wesslen", "raw_affiliation_strings": ["University of North Carolina at Charlotte"], "affiliations": [{"raw_affiliation_string": "University of North Carolina at Charlotte", "institution_ids": ["https://openalex.org/I102149020"]}]}, {"author_position": "middle", "author": {"id": "https://openalex.org/A5102996367", "display_name": "Svitlana Volkova", "orcid": "https://orcid.org/0000-0002-6131-3073"}, "institutions": [{"id": "https://openalex.org/I142606810", "display_name": "Pacific Northwest National Laboratory", "ror": "https://ror.org/05h992307", "country_code": "US", "type": "facility", "lineage": ["https://openalex.org/I1325736334", "https://openalex.org/I1330989302", "https://openalex.org/I142606810", "https://openalex.org/I39565521"]}], "countries": ["US"], "is_corresponding": false, "raw_author_name": "Svitlana Volkova", "raw_affiliation_strings": ["Pacific Northwest National Laboratory"], "affiliations": [{"raw_affiliation_string": "Pacific Northwest National Laboratory", "institution_ids": ["https://openalex.org/I142606810"]}]}, {"author_position": "middle", "author": {"id": "https://openalex.org/A5110208682", "display_name": "William Ribarsky", "orcid": null}, "institutions": [{"id": "https://openalex.org/I102149020", "display_name": "University of North Carolina at Charlotte", "ror": "https://ror.org/04dawnj30", "country_code": "US", "type": "education", "lineage": ["https://openalex.org/I102149020"]}], "countries": ["US"], "is_corresponding": false, "raw_author_name": "William Ribarsky", "raw_affiliation_strings": ["University of North Carolina at Charlotte"], "affiliations": [{"raw_affiliation_string": "University of North Carolina at Charlotte", "institution_ids": ["https://openalex.org/I102149020"]}]}, {"author_position": "last", "author": {"id": "https://openalex.org/A5055992752", "display_name": "Wenwen Dou", "orcid": "https://orcid.org/0000-0003-0319-9484"}, "institutions": [{"id": "https://openalex.org/I102149020", "display_name": "University of North Carolina at Charlotte", "ror": "https://ror.org/04dawnj30", "country_code": "US", "type": "education", "lineage": ["https://openalex.org/I102149020"]}], "countries": ["US"], "is_corresponding": false, "raw_author_name": "Wenwen Dou", "raw_affiliation_strings": ["University of North Carolina at Charlotte"], "affiliations": [{"raw_affiliation_string": "University of North Carolina at Charlotte", "institution_ids": ["https://openalex.org/I102149020"]}]}], "institutions": [], "countries_distinct_count": 1, "institutions_distinct_count": 5, "corresponding_author_ids": [], "corresponding_institution_ids": [], "apc_list": null, "apc_paid": null, "fwci": 1.89810588, "has_fulltext": false, "cited_by_count": 15, "citation_normalized_percentile": {"value": 0.86471629, "is_in_top_1_percent": false, "is_in_top_10_percent": false}, "cited_by_percentile_year": {"min": 89, "max": 98}, "biblio": {"volume": null, "issue": null, "first_page": "25", "last_page": "35"}, "is_retracted": false, "is_paratext": false, "is_xpac": false, "primary_topic": {"id": "https://openalex.org/T10064", "display_name": "Complex Network Analysis Techniques", "score": 0.9987999796867371, "subfield": {"id": "https://openalex.org/subfields/3109", "display_name": "Statistical and Nonlinear Physics"}, "field": {"id": "https://openalex.org/fields/31", "display_name": "Physics and Astronomy"}, "domain": {"id": "https://openalex.org/domains/3", "display_name": "Physical Sciences"}}, "topics": [{"id": "https://openalex.org/T10064", "display_name": "Complex Network Analysis Techniques", "score": 0.9987999796867371, "subfield": {"id": "https://openalex.org/subfields/3109", "display_name": "Statistical and Nonlinear Physics"}, "field": {"id": "https://openalex.org/fields/31", "display_name": "Physics and Astronomy"}, "domain": {"id": "https://openalex.org/domains/3", "display_name": "Physical Sciences"}}, {"id": "https://openalex.org/T10799", "display_name": "Data Visualization and Analytics", "score": 0.998199999332428, "subfield": {"id": "https://openalex.org/subfields/1707", "display_name": "Computer Vision and Pattern Recognition"}, "field": {"id": "https://openalex.org/fields/17", "display_name": "Computer Science"}, "domain": {"id": "https://openalex.org/domains/3", "display_name": "Physical Sciences"}}, {"id": "https://openalex.org/T12016", "display_name": "Web Data Mining and Analysis", "score": 0.9907000064849854, "subfield": {"id": "https://openalex.org/subfields/1710", "display_name": "Information Systems"}, "field": {"id": "https://openalex.org/fields/17", "display_name": "Computer Science"}, "domain": {"id": "https://openalex.org/domains/3", "display_name": "Physical Sciences"}}], "keywords": [{"id": "https://openalex.org/keywords/computer-science", "display_name": "Computer science", "score": 0.8305286169052124}, {"id": "https://openalex.org/keywords/sensemaking", "display_name": "Sensemaking", "score": 0.7987004518508911}, {"id": "https://openalex.org/keywords/social-media", "display_name": "Social media", "score": 0.6630668640136719}, {"id": "https://openalex.org/keywords/data-science", "display_name": "Data science", "score": 0.6518462896347046}, {"id": "https://openalex.org/keywords/event", "display_name": "Event (particle physics)", "score": 0.6250696182250977}, {"id": "https://openalex.org/keywords/visual-analytics", "display_name": "Visual analytics", "score": 0.6147816181182861}, {"id": "https://openalex.org/keywords/visualization", "display_name": "Visualization", "score": 0.5469820499420166}, {"id": "https://openalex.org/keywords/data-visualization", "display_name": "Data visualization", "score": 0.48794883489608765}, {"id": "https://openalex.org/keywords/graph", "display_name": "Graph", "score": 0.4585234522819519}, {"id": "https://openalex.org/keywords/interactive-visual-analysis", "display_name": "Interactive visual analysis", "score": 0.44536393880844116}, {"id": "https://openalex.org/keywords/information-retrieval", "display_name": "Information retrieval", "score": 0.3847216069698334}, {"id": "https://openalex.org/keywords/human–computer-interaction", "display_name": "Human–computer interaction", "score": 0.3591988682746887}, {"id": "https://openalex.org/keywords/world-wide-web", "display_name": "World Wide Web", "score": 0.2849147617816925}, {"id": "https://openalex.org/keywords/data-mining", "display_name": "Data mining", "score": 0.25694501399993896}, {"id": "https://openalex.org/keywords/theoretical-computer-science", "display_name": "Theoretical computer science", "score": 0.10672721266746521}], "concepts": [{"id": "https://openalex.org/C41008148", "wikidata": "https://www.wikidata.org/wiki/Q21198", "display_name": "Computer science", "level": 0, "score": 0.8305286169052124}, {"id": "https://openalex.org/C2780554381", "wikidata": "https://www.wikidata.org/wiki/Q2063340", "display_name": "Sensemaking", "level": 2, "score": 0.7987004518508911}, {"id": "https://openalex.org/C518677369", "wikidata": "https://www.wikidata.org/wiki/Q202833", "display_name": "Social media", "level": 2, "score": 0.6630668640136719}, {"id": "https://openalex.org/C2522767166", "wikidata": "https://www.wikidata.org/wiki/Q2374463", "display_name": "Data science", "level": 1, "score": 0.6518462896347046}, {"id": "https://openalex.org/C2779662365", "wikidata": "https://www.wikidata.org/wiki/Q5416694", "display_name": "Event (particle physics)", "level": 2, "score": 0.6250696182250977}, {"id": "https://openalex.org/C59732488", "wikidata": "https://www.wikidata.org/wiki/Q2528440", "display_name": "Visual analytics", "level": 3, "score": 0.6147816181182861}, {"id": "https://openalex.org/C36464697", "wikidata": "https://www.wikidata.org/wiki/Q451553", "display_name": "Visualization", "level": 2, "score": 0.5469820499420166}, {"id": "https://openalex.org/C172367668", "wikidata": "https://www.wikidata.org/wiki/Q6504956", "display_name": "Data visualization", "level": 3, "score": 0.48794883489608765}, {"id": "https://openalex.org/C132525143", "wikidata": "https://www.wikidata.org/wiki/Q141488", "display_name": "Graph", "level": 2, "score": 0.4585234522819519}, {"id": "https://openalex.org/C99740376", "wikidata": "https://www.wikidata.org/wiki/Q17092520", "display_name": "Interactive visual analysis", "level": 4, "score": 0.44536393880844116}, {"id": "https://openalex.org/C23123220", "wikidata": "https://www.wikidata.org/wiki/Q816826", "display_name": "Information retrieval", "level": 1, "score": 0.3847216069698334}, {"id": "https://openalex.org/C107457646", "wikidata": "https://www.wikidata.org/wiki/Q207434", "display_name": "Human–computer interaction", "level": 1, "score": 0.3591988682746887}, {"id": "https://openalex.org/C136764020", "wikidata": "https://www.wikidata.org/wiki/Q466", "display_name": "World Wide Web", "level": 1, "score": 0.2849147617816925}, {"id": "https://openalex.org/C124101348", "wikidata": "https://www.wikidata.org/wiki/Q172491", "display_name": "Data mining", "level": 1, "score": 0.25694501399993896}, {"id": "https://openalex.org/C80444323", "wikidata": "https://www.wikidata.org/wiki/Q2878974", "display_name": "Theoretical computer science", "level": 1, "score": 0.10672721266746521}, {"id": "https://openalex.org/C62520636", "wikidata": "https://www.wikidata.org/wiki/Q944", "display_name": "Quantum mechanics", "level": 1, "score": 0.0}, {"id": "https://openalex.org/C121332964", "wikidata": "https://www.wikidata.org/wiki/Q413", "display_name": "Physics", "level": 0, "score": 0.0}], "mesh": [], "locations_count": 1, "locations": [{"id": "doi:10.1109/vast.2017.8585658", "is_oa": false, "landing_page_url": "https://doi.org/10.1109/vast.2017.8585658", "pdf_url": null, "source": null, "license": null, "license_id": null, "version": "publishedVersion", "is_accepted": true, "is_published": true, "raw_source_name": "2017 IEEE Conference on Visual Analytics Science and Technology (VAST)", "raw_type": "proceedings-article"}], "best_oa_location": null, "sustainable_development_goals": [], "awards": [], "funders": [], "has_content": {"grobid_xml": false, "pdf": false}, "referenced_works_count": 39, "referenced_works": ["https://openalex.org/W2163898372", "https://openalex.org/W6697152160", "https://openalex.org/W1973803644", "https://openalex.org/W2542459869", "https://openalex.org/W1998224037", "https://openalex.org/W1958900514", "https://openalex.org/W2100298478", "https://openalex.org/W6687182693", "https://openalex.org/W2021001446", "https://openalex.org/W6684152816", "https://openalex.org/W2056944867", "https://openalex.org/W2003146622", "https://openalex.org/W6685234327", "https://openalex.org/W2047221353", "https://openalex.org/W2123661878", "https://openalex.org/W6682707525", "https://openalex.org/W2741512591", "https://openalex.org/W6631502387", "https://openalex.org/W1998032016", "https://openalex.org/W6751854905", "https://openalex.org/W1973897992", "https://openalex.org/W6691573161", "https://openalex.org/W6636915900", "https://openalex.org/W2142865875", "https://openalex.org/W2109552221", "https://openalex.org/W2048968173", "https://openalex.org/W6612627285", "https://openalex.org/W2195876357", "https://openalex.org/W2165279024", "https://openalex.org/W1559945916", "https://openalex.org/W2251758222", "https://openalex.org/W1647671624", "https://openalex.org/W2172553180", "https://openalex.org/W1528377600", "https://openalex.org/W2803437449", "https://openalex.org/W2398670371", "https://openalex.org/W2293267779", "https://openalex.org/W2153848201", "https://openalex.org/W371426616"], "related_works": ["https://openalex.org/W2362367986", "https://openalex.org/W3041760129", "https://openalex.org/W3149127250", "https://openalex.org/W2158984754", "https://openalex.org/W2143428259", "https://openalex.org/W4246764483", "https://openalex.org/W2923661510", "https://openalex.org/W2081749267", "https://openalex.org/W2116732611", "https://openalex.org/W2080934634"], "abstract_inverted_index": {"Social": [0], "media": [1, 38], "data": [2], "bear": [3], "valuable": [4], "insights": [5], "regarding": [6, 104], "events": [7, 43, 67, 77, 160, 175], "that": [8, 44, 61, 81], "occur": [9, 46], "around": [10], "the": [11, 48, 85, 110, 113, 122, 131, 145, 148, 153], "world.": [12], "Events": [13], "are": [14, 141], "inherently": [15], "temporal": [16], "and": [17, 28, 31, 64, 98, 109, 139, 161, 170], "spatial.": [18], "Existing": [19], "visual": [20, 57, 116], "text": [21], "analysis": [22], "systems": [23], "have": [24, 35], "focused": [25], "on": [26, 173], "detecting": [27], "analyzing": [29, 174], "past": [30], "ongoing": [32], "events.": [33, 88, 134, 150], "Few": [34], "leveraged": [36], "social": [37, 107], "information": [39, 103], "to": [40, 75, 96, 125, 143], "look": [41], "for": [42], "may": [45], "in": [47, 157], "future.": [49], "In": [50], "this": [51], "paper,": [52], "we": [53, 165], "present": [54, 126, 166], "an": [55], "interactive": [56, 79, 163], "analytic": [58], "system,": [59], "CrystalBall,": [60], "automatically": [62], "identifies": [63], "ranks": [65], "future": [66, 87, 100, 133, 149, 159], "from": [68, 177], "Twitter": [69, 178], "streams.": [70], "CrystalBall": [71, 156], "integrates": [72], "new": [73], "methods": [74, 91, 124], "discover": [76], "with": [78, 121], "visualizations": [80], "permit": [82], "sensemaking": [83], "of": [84, 112, 130, 147, 155], "identified": [86], "Our": [89], "computational": [90, 123], "integrate": [92], "seven": [93], "different": [94], "measures": [95], "identify": [97], "characterize": [99], "events,": [101], "leveraging": [102], "time,": [105], "location,": [106], "networks,": [108], "informativeness": [111], "messages.": [114], "A": [115, 135], "interface": [117], "is": [118], "tightly": [119], "coupled": [120], "a": [127], "concise": [128], "summary": [129], "possible": [132], "novel": [136], "connection": [137], "graph": [138], "glyphs": [140], "designed": [142], "visualize": [144], "characteristics": [146], "To": [151], "demonstrate": [152], "efficacy": [154], "identifying": [158], "supporting": [162], "analysis,": [164], "multiple": [167], "case": [168], "studies": [169, 172], "validation": [171], "derived": [176], "data.": [179]}, "counts_by_year": [{"year": 2025, "cited_by_count": 1}, {"year": 2024, "cited_by_count": 1}, {"year": 2023, "cited_by_count": 1}, {"year": 2022, "cited_by_count": 1}, {"year": 2021, "cited_by_count": 1}, {"year": 2020, "cited_by_count": 2}, {"year": 2019, "cited_by_count": 2}, {"year": 2018, "cited_by_count": 5}, {"year": 2017, "cited_by_count": 1}], "updated_date": "2025-11-06T03:46:38.306776", "created_date": "2025-10-10T00:00:00"}