{"id": "https://openalex.org/W2044135788", "doi": "https://doi.org/10.1109/vast.2009.5333878", "title": "Evaluating visual analytics systems for investigative analysis: Deriving design principles from a case study", "display_name": "Evaluating visual analytics systems for investigative analysis: Deriving design principles from a case study", "publication_year": 2009, "publication_date": "2009-01-01", "ids": {"openalex": "https://openalex.org/W2044135788", "doi": "https://doi.org/10.1109/vast.2009.5333878", "mag": "2044135788"}, "language": "en", "primary_location": {"id": "doi:10.1109/vast.2009.5333878", "is_oa": false, "landing_page_url": "https://doi.org/10.1109/vast.2009.5333878", "pdf_url": null, "source": null, "license": null, "license_id": null, "version": "publishedVersion", "is_accepted": true, "is_published": true, "raw_source_name": "2009 IEEE Symposium on Visual Analytics Science and Technology", "raw_type": "proceedings-article"}, "type": "article", "indexed_in": ["crossref"], "open_access": {"is_oa": false, "oa_status": "closed", "oa_url": null, "any_repository_has_fulltext": false}, "authorships": [{"author_position": "first", "author": {"id": "https://openalex.org/A5088085186", "display_name": "Younah Kang", "orcid": "https://orcid.org/0000-0003-4981-6329"}, "institutions": [{"id": "https://openalex.org/I130701444", "display_name": "Georgia Institute of Technology", "ror": "https://ror.org/01zkghx44", "country_code": "US", "type": "education", "lineage": ["https://openalex.org/I130701444"]}], "countries": ["US"], "is_corresponding": false, "raw_author_name": "Youn-ah Kang", "raw_affiliation_strings": ["[School of Interactive Computing & GVU Center, Georgia Institute of Technology, USA]"], "affiliations": [{"raw_affiliation_string": "[School of Interactive Computing & GVU Center, Georgia Institute of Technology, USA]", "institution_ids": ["https://openalex.org/I130701444"]}]}, {"author_position": "middle", "author": {"id": "https://openalex.org/A5064020522", "display_name": "Carsten Görg", "orcid": "https://orcid.org/0000-0001-5088-4201"}, "institutions": [{"id": "https://openalex.org/I130701444", "display_name": "Georgia Institute of Technology", "ror": "https://ror.org/01zkghx44", "country_code": "US", "type": "education", "lineage": ["https://openalex.org/I130701444"]}], "countries": ["US"], "is_corresponding": false, "raw_author_name": "Carsten Gorg", "raw_affiliation_strings": ["[School of Interactive Computing & GVU Center, Georgia Institute of Technology, USA]"], "affiliations": [{"raw_affiliation_string": "[School of Interactive Computing & GVU Center, Georgia Institute of Technology, USA]", "institution_ids": ["https://openalex.org/I130701444"]}]}, {"author_position": "last", "author": {"id": "https://openalex.org/A5082668404", "display_name": "John Stasko", "orcid": "https://orcid.org/0000-0003-4129-7659"}, "institutions": [{"id": "https://openalex.org/I130701444", "display_name": "Georgia Institute of Technology", "ror": "https://ror.org/01zkghx44", "country_code": "US", "type": "education", "lineage": ["https://openalex.org/I130701444"]}], "countries": ["US"], "is_corresponding": false, "raw_author_name": "John Stasko", "raw_affiliation_strings": ["[School of Interactive Computing & GVU Center, Georgia Institute of Technology, USA]"], "affiliations": [{"raw_affiliation_string": "[School of Interactive Computing & GVU Center, Georgia Institute of Technology, USA]", "institution_ids": ["https://openalex.org/I130701444"]}]}], "institutions": [], "countries_distinct_count": 1, "institutions_distinct_count": 3, "corresponding_author_ids": [], "corresponding_institution_ids": [], "apc_list": null, "apc_paid": null, "fwci": 8.06042904, "has_fulltext": false, "cited_by_count": 90, "citation_normalized_percentile": {"value": 0.98205103, "is_in_top_1_percent": false, "is_in_top_10_percent": true}, "cited_by_percentile_year": {"min": 89, "max": 99}, "biblio": {"volume": null, "issue": null, "first_page": "139", "last_page": "146"}, "is_retracted": false, "is_paratext": false, "is_xpac": false, "primary_topic": {"id": "https://openalex.org/T10799", "display_name": "Data Visualization and Analytics", "score": 0.9998000264167786, "subfield": {"id": "https://openalex.org/subfields/1707", "display_name": "Computer Vision and Pattern Recognition"}, "field": {"id": "https://openalex.org/fields/17", "display_name": "Computer Science"}, "domain": {"id": "https://openalex.org/domains/3", "display_name": "Physical Sciences"}}, "topics": [{"id": "https://openalex.org/T10799", "display_name": "Data Visualization and Analytics", "score": 0.9998000264167786, "subfield": {"id": "https://openalex.org/subfields/1707", "display_name": "Computer Vision and Pattern Recognition"}, "field": {"id": "https://openalex.org/fields/17", "display_name": "Computer Science"}, "domain": {"id": "https://openalex.org/domains/3", "display_name": "Physical Sciences"}}, {"id": "https://openalex.org/T12859", "display_name": "Cell Image Analysis Techniques", "score": 0.9700000286102295, "subfield": {"id": "https://openalex.org/subfields/1304", "display_name": "Biophysics"}, "field": {"id": "https://openalex.org/fields/13", "display_name": "Biochemistry, Genetics and Molecular Biology"}, "domain": {"id": "https://openalex.org/domains/1", "display_name": "Life Sciences"}}, {"id": "https://openalex.org/T11986", "display_name": "Scientific Computing and Data Management", "score": 0.9386000037193298, "subfield": {"id": "https://openalex.org/subfields/1802", "display_name": "Information Systems and Management"}, "field": {"id": "https://openalex.org/fields/18", "display_name": "Decision Sciences"}, "domain": {"id": "https://openalex.org/domains/2", "display_name": "Social Sciences"}}], "keywords": [{"id": "https://openalex.org/keywords/sensemaking", "display_name": "Sensemaking", "score": 0.9011045694351196}, {"id": "https://openalex.org/keywords/jigsaw", "display_name": "Jigsaw", "score": 0.8513398766517639}, {"id": "https://openalex.org/keywords/visual-analytics", "display_name": "Visual analytics", "score": 0.7599531412124634}, {"id": "https://openalex.org/keywords/computer-science", "display_name": "Computer science", "score": 0.731450080871582}, {"id": "https://openalex.org/keywords/intelligence-analysis", "display_name": "Intelligence analysis", "score": 0.7006556391716003}, {"id": "https://openalex.org/keywords/data-science", "display_name": "Data science", "score": 0.5777568817138672}, {"id": "https://openalex.org/keywords/analytics", "display_name": "Analytics", "score": 0.5224370360374451}, {"id": "https://openalex.org/keywords/task", "display_name": "Task (project management)", "score": 0.4980909824371338}, {"id": "https://openalex.org/keywords/cultural-analytics", "display_name": "Cultural analytics", "score": 0.45979711413383484}, {"id": "https://openalex.org/keywords/process", "display_name": "Process (computing)", "score": 0.4514724612236023}, {"id": "https://openalex.org/keywords/empirical-research", "display_name": "Empirical research", "score": 0.44374707341194153}, {"id": "https://openalex.org/keywords/knowledge-management", "display_name": "Knowledge management", "score": 0.38691139221191406}, {"id": "https://openalex.org/keywords/human–computer-interaction", "display_name": "Human–computer interaction", "score": 0.36927998065948486}, {"id": "https://openalex.org/keywords/visualization", "display_name": "Visualization", "score": 0.35251322388648987}, {"id": "https://openalex.org/keywords/management-science", "display_name": "Management science", "score": 0.347502738237381}, {"id": "https://openalex.org/keywords/artificial-intelligence", "display_name": "Artificial intelligence", "score": 0.21610653400421143}, {"id": "https://openalex.org/keywords/psychology", "display_name": "Psychology", "score": 0.16953524947166443}, {"id": "https://openalex.org/keywords/engineering", "display_name": "Engineering", "score": 0.12157690525054932}, {"id": "https://openalex.org/keywords/systems-engineering", "display_name": "Systems engineering", "score": 0.11611154675483704}, {"id": "https://openalex.org/keywords/semantic-analytics", "display_name": "Semantic analytics", "score": 0.10845470428466797}], "concepts": [{"id": "https://openalex.org/C2780554381", "wikidata": "https://www.wikidata.org/wiki/Q2063340", "display_name": "Sensemaking", "level": 2, "score": 0.9011045694351196}, {"id": "https://openalex.org/C2779405079", "wikidata": "https://www.wikidata.org/wiki/Q356040", "display_name": "Jigsaw", "level": 2, "score": 0.8513398766517639}, {"id": "https://openalex.org/C59732488", "wikidata": "https://www.wikidata.org/wiki/Q2528440", "display_name": "Visual analytics", "level": 3, "score": 0.7599531412124634}, {"id": "https://openalex.org/C41008148", "wikidata": "https://www.wikidata.org/wiki/Q21198", "display_name": "Computer science", "level": 0, "score": 0.731450080871582}, {"id": "https://openalex.org/C517642484", "wikidata": "https://www.wikidata.org/wiki/Q2388514", "display_name": "Intelligence analysis", "level": 2, "score": 0.7006556391716003}, {"id": "https://openalex.org/C2522767166", "wikidata": "https://www.wikidata.org/wiki/Q2374463", "display_name": "Data science", "level": 1, "score": 0.5777568817138672}, {"id": "https://openalex.org/C79158427", "wikidata": "https://www.wikidata.org/wiki/Q485396", "display_name": "Analytics", "level": 2, "score": 0.5224370360374451}, {"id": "https://openalex.org/C2780451532", "wikidata": "https://www.wikidata.org/wiki/Q759676", "display_name": "Task (project management)", "level": 2, "score": 0.4980909824371338}, {"id": "https://openalex.org/C545860419", "wikidata": "https://www.wikidata.org/wiki/Q5193251", "display_name": "Cultural analytics", "level": 5, "score": 0.45979711413383484}, {"id": "https://openalex.org/C98045186", "wikidata": "https://www.wikidata.org/wiki/Q205663", "display_name": "Process (computing)", "level": 2, "score": 0.4514724612236023}, {"id": "https://openalex.org/C120936955", "wikidata": "https://www.wikidata.org/wiki/Q2155640", "display_name": "Empirical research", "level": 2, "score": 0.44374707341194153}, {"id": "https://openalex.org/C56739046", "wikidata": "https://www.wikidata.org/wiki/Q192060", "display_name": "Knowledge management", "level": 1, "score": 0.38691139221191406}, {"id": "https://openalex.org/C107457646", "wikidata": "https://www.wikidata.org/wiki/Q207434", "display_name": "Human–computer interaction", "level": 1, "score": 0.36927998065948486}, {"id": "https://openalex.org/C36464697", "wikidata": "https://www.wikidata.org/wiki/Q451553", "display_name": "Visualization", "level": 2, "score": 0.35251322388648987}, {"id": "https://openalex.org/C539667460", "wikidata": "https://www.wikidata.org/wiki/Q2414942", "display_name": "Management science", "level": 1, "score": 0.347502738237381}, {"id": "https://openalex.org/C154945302", "wikidata": "https://www.wikidata.org/wiki/Q11660", "display_name": "Artificial intelligence", "level": 1, "score": 0.21610653400421143}, {"id": "https://openalex.org/C15744967", "wikidata": "https://www.wikidata.org/wiki/Q9418", "display_name": "Psychology", "level": 0, "score": 0.16953524947166443}, {"id": "https://openalex.org/C127413603", "wikidata": "https://www.wikidata.org/wiki/Q11023", "display_name": "Engineering", "level": 0, "score": 0.12157690525054932}, {"id": "https://openalex.org/C201995342", "wikidata": "https://www.wikidata.org/wiki/Q682496", "display_name": "Systems engineering", "level": 1, "score": 0.11611154675483704}, {"id": "https://openalex.org/C148792806", "wikidata": "https://www.wikidata.org/wiki/Q7449046", "display_name": "Semantic analytics", "level": 4, "score": 0.10845470428466797}, {"id": "https://openalex.org/C2129575", "wikidata": "https://www.wikidata.org/wiki/Q54837", "display_name": "Semantic Web", "level": 2, "score": 0.0}, {"id": "https://openalex.org/C138885662", "wikidata": "https://www.wikidata.org/wiki/Q5891", "display_name": "Philosophy", "level": 0, "score": 0.0}, {"id": "https://openalex.org/C111919701", "wikidata": "https://www.wikidata.org/wiki/Q9135", "display_name": "Operating system", "level": 1, "score": 0.0}, {"id": "https://openalex.org/C111472728", "wikidata": "https://www.wikidata.org/wiki/Q9471", "display_name": "Epistemology", "level": 1, "score": 0.0}, {"id": "https://openalex.org/C167379230", "wikidata": "https://www.wikidata.org/wiki/Q1026884", "display_name": "Semantic Web Stack", "level": 3, "score": 0.0}, {"id": "https://openalex.org/C38652104", "wikidata": "https://www.wikidata.org/wiki/Q3510521", "display_name": "Computer security", "level": 1, "score": 0.0}, {"id": "https://openalex.org/C19417346", "wikidata": "https://www.wikidata.org/wiki/Q7922", "display_name": "Pedagogy", "level": 1, "score": 0.0}], "mesh": [], "locations_count": 1, "locations": [{"id": "doi:10.1109/vast.2009.5333878", "is_oa": false, "landing_page_url": "https://doi.org/10.1109/vast.2009.5333878", "pdf_url": null, "source": null, "license": null, "license_id": null, "version": "publishedVersion", "is_accepted": true, "is_published": true, "raw_source_name": "2009 IEEE Symposium on Visual Analytics Science and Technology", "raw_type": "proceedings-article"}], "best_oa_location": null, "sustainable_development_goals": [], "awards": [], "funders": [{"id": "https://openalex.org/F4320306076", "display_name": "National Science Foundation", "ror": "https://ror.org/021nxhr62"}, {"id": "https://openalex.org/F4320306110", "display_name": "U.S. Department of Homeland Security", "ror": "https://ror.org/00jyr0d86"}], "has_content": {"pdf": false, "grobid_xml": false}, "referenced_works_count": 16, "referenced_works": ["https://openalex.org/W1992928607", "https://openalex.org/W4248481136", "https://openalex.org/W2138199375", "https://openalex.org/W2157887077", "https://openalex.org/W2130774862", "https://openalex.org/W2148269024", "https://openalex.org/W2053864527", "https://openalex.org/W2057718781", "https://openalex.org/W2077290111", "https://openalex.org/W1997901969", "https://openalex.org/W2055175765", "https://openalex.org/W2082471240", "https://openalex.org/W2144320230", "https://openalex.org/W2168440500", "https://openalex.org/W2169700383", "https://openalex.org/W2165662062"], "related_works": ["https://openalex.org/W2243254447", "https://openalex.org/W4387891525", "https://openalex.org/W1995144346", "https://openalex.org/W2147539779", "https://openalex.org/W3022092363", "https://openalex.org/W3043419493", "https://openalex.org/W1984700945", "https://openalex.org/W595934349", "https://openalex.org/W1991558104", "https://openalex.org/W2171519016"], "abstract_inverted_index": {"Despite": [0], "the": [1, 17, 65, 78, 114, 126, 147, 151, 159, 164], "growing": [2], "number": [3], "of": [4, 16, 20, 67, 77, 101, 113, 158], "systems": [5, 22, 33, 55, 69], "providing": [6], "visual": [7, 79, 187], "analytic": [8], "support": [9, 145], "for": [10, 40, 170, 180, 184], "investigative": [11, 87, 171, 189], "analysis,": [12], "few": [13], "empirical": [14], "studies": [15, 48], "potential": [18], "benefits": [19], "such": [21, 32, 54], "have": [23], "been": [24], "conducted,": [25], "particularly": [26], "controlled,": [27], "comparative": [28], "evaluations.": [29], "Determining": [30], "how": [31, 51, 143], "foster": [34], "insight": [35], "and": [36, 44, 56, 90, 128, 142, 166, 182], "sensemaking": [37, 88, 160], "is": [38], "important": [39], "their": [41], "continued": [42], "growth": [43], "study,": [45], "however.": [46], "Furthermore,": [47], "that": [49, 120], "identify": [50, 129], "people": [52], "use": [53, 94], "why": [57], "they": [58], "benefit": [59], "(or": [60, 146], "not)": [61], "can": [62], "help": [63], "inform": [64], "design": [66, 168], "new": [68], "in": [70, 84, 163], "this": [71], "area.": [72], "We": [73, 133, 153, 176], "conducted": [74], "an": [75, 130], "evaluation": [76], "analytics": [80, 188], "system": [81], "Jigsaw": [82, 121], "employed": [83], "a": [85, 106], "small": [86], "exercise,": [89], "we": [91], "compared": [92], "its": [93], "to": [95, 124], "three": [96], "other": [97, 186], "more": [98], "traditional": [99], "methods": [100], "analysis.": [102], "Sixteen": [103], "participants": [104, 123, 141], "performed": [105], "simulated": [107], "intelligence": [108], "analysis": [109, 136, 172, 190], "task": [110], "under": [111], "one": [112], "four": [115], "conditions.": [116], "Experimental": [117], "results": [118], "suggest": [119], "assisted": [122], "analyze": [125], "data": [127], "embedded": [131], "threat.": [132], "describe": [134], "different": [135], "strategies": [137], "used": [138], "by": [139], "study": [140, 165], "computational": [144], "lack": [148], "thereof)": [149], "influenced": [150], "strategies.": [152], "then": [154], "illustrate": [155], "several": [156], "characteristics": [157], "process": [161], "identified": [162], "provide": [167], "implications": [169], "tools": [173], "based": [174], "thereon.": [175], "conclude": [177], "with": [178], "recommendations": [179], "metrics": [181], "techniques": [183], "evaluating": [185], "tools.": [191]}, "counts_by_year": [{"year": 2024, "cited_by_count": 4}, {"year": 2023, "cited_by_count": 5}, {"year": 2022, "cited_by_count": 5}, {"year": 2021, "cited_by_count": 1}, {"year": 2020, "cited_by_count": 5}, {"year": 2019, "cited_by_count": 3}, {"year": 2018, "cited_by_count": 4}, {"year": 2017, "cited_by_count": 11}, {"year": 2016, "cited_by_count": 3}, {"year": 2015, "cited_by_count": 9}, {"year": 2014, "cited_by_count": 7}, {"year": 2013, "cited_by_count": 7}, {"year": 2012, "cited_by_count": 8}], "updated_date": "2025-11-06T03:46:38.306776", "created_date": "2025-10-10T00:00:00"}