{"id": "https://openalex.org/W3145929700", "doi": "https://doi.org/10.1109/infvis.2004.15", "title": "Clutter Reduction in Multi-Dimensional Data Visualization Using Dimension Reordering", "display_name": "Clutter Reduction in Multi-Dimensional Data Visualization Using Dimension Reordering", "publication_year": 2005, "publication_date": "2005-04-06", "ids": {"openalex": "https://openalex.org/W3145929700", "doi": "https://doi.org/10.1109/infvis.2004.15", "mag": "3145929700"}, "language": "en", "primary_location": {"id": "doi:10.1109/infvis.2004.15", "is_oa": false, "landing_page_url": "https://doi.org/10.1109/infvis.2004.15", "pdf_url": null, "source": {"id": "https://openalex.org/S4306418832", "display_name": "IEEE Symposium on Information Visualization", "issn_l": null, "issn": null, "is_oa": false, "is_in_doaj": false, "is_core": false, "host_organization": null, "host_organization_name": null, "host_organization_lineage": [], "host_organization_lineage_names": [], "type": "conference"}, "license": null, "license_id": null, "version": "publishedVersion", "is_accepted": true, "is_published": true, "raw_source_name": "IEEE Symposium on Information Visualization", "raw_type": "proceedings-article"}, "type": "article", "indexed_in": ["crossref"], "open_access": {"is_oa": false, "oa_status": "closed", "oa_url": null, "any_repository_has_fulltext": false}, "authorships": [{"author_position": "first", "author": {"id": "https://openalex.org/A5019479187", "display_name": "Wei Peng", "orcid": "https://orcid.org/0000-0002-2892-5764"}, "institutions": [{"id": "https://openalex.org/I107077323", "display_name": "Worcester Polytechnic Institute", "ror": "https://ror.org/05ejpqr48", "country_code": "US", "type": "education", "lineage": ["https://openalex.org/I107077323"]}], "countries": ["US"], "is_corresponding": false, "raw_author_name": "None Wei Peng", "raw_affiliation_strings": ["Computer Science Department, Worcester Polytechnic Institute, Worcester, MA, USA"], "affiliations": [{"raw_affiliation_string": "Computer Science Department, Worcester Polytechnic Institute, Worcester, MA, USA", "institution_ids": ["https://openalex.org/I107077323"]}]}, {"author_position": "middle", "author": {"id": "https://openalex.org/A5102773082", "display_name": "Matthew O. Ward", "orcid": "https://orcid.org/0000-0002-3080-2579"}, "institutions": [{"id": "https://openalex.org/I107077323", "display_name": "Worcester Polytechnic Institute", "ror": "https://ror.org/05ejpqr48", "country_code": "US", "type": "education", "lineage": ["https://openalex.org/I107077323"]}], "countries": ["US"], "is_corresponding": false, "raw_author_name": "M.O. Ward", "raw_affiliation_strings": ["Computer Science Department, Worcester Polytechnic Institute, Worcester, MA, USA"], "affiliations": [{"raw_affiliation_string": "Computer Science Department, Worcester Polytechnic Institute, Worcester, MA, USA", "institution_ids": ["https://openalex.org/I107077323"]}]}, {"author_position": "last", "author": {"id": "https://openalex.org/A5008269094", "display_name": "Elke A. Rundensteiner", "orcid": "https://orcid.org/0000-0001-5375-9254"}, "institutions": [{"id": "https://openalex.org/I107077323", "display_name": "Worcester Polytechnic Institute", "ror": "https://ror.org/05ejpqr48", "country_code": "US", "type": "education", "lineage": ["https://openalex.org/I107077323"]}], "countries": ["US"], "is_corresponding": false, "raw_author_name": "E.A. Rundensteiner", "raw_affiliation_strings": ["Computer Science Department, Worcester Polytechnic Institute, Worcester, MA, USA"], "affiliations": [{"raw_affiliation_string": "Computer Science Department, Worcester Polytechnic Institute, Worcester, MA, USA", "institution_ids": ["https://openalex.org/I107077323"]}]}], "institutions": [], "countries_distinct_count": 1, "institutions_distinct_count": 3, "corresponding_author_ids": [], "corresponding_institution_ids": [], "apc_list": null, "apc_paid": null, "fwci": 9.13904842, "has_fulltext": false, "cited_by_count": 162, "citation_normalized_percentile": {"value": 0.98676171, "is_in_top_1_percent": false, "is_in_top_10_percent": true}, "cited_by_percentile_year": {"min": 97, "max": 100}, "biblio": {"volume": null, "issue": null, "first_page": "89", "last_page": "96"}, "is_retracted": false, "is_paratext": false, "is_xpac": false, "primary_topic": {"id": "https://openalex.org/T10799", "display_name": "Data Visualization and Analytics", "score": 0.9994999766349792, "subfield": {"id": "https://openalex.org/subfields/1707", "display_name": "Computer Vision and Pattern Recognition"}, "field": {"id": "https://openalex.org/fields/17", "display_name": "Computer Science"}, "domain": {"id": "https://openalex.org/domains/3", "display_name": "Physical Sciences"}}, "topics": [{"id": "https://openalex.org/T10799", "display_name": "Data Visualization and Analytics", "score": 0.9994999766349792, "subfield": {"id": "https://openalex.org/subfields/1707", "display_name": "Computer Vision and Pattern Recognition"}, "field": {"id": "https://openalex.org/fields/17", "display_name": "Computer Science"}, "domain": {"id": "https://openalex.org/domains/3", "display_name": "Physical Sciences"}}, {"id": "https://openalex.org/T11439", "display_name": "Video Analysis and Summarization", "score": 0.9897000193595886, "subfield": {"id": "https://openalex.org/subfields/1707", "display_name": "Computer Vision and Pattern Recognition"}, "field": {"id": "https://openalex.org/fields/17", "display_name": "Computer Science"}, "domain": {"id": "https://openalex.org/domains/3", "display_name": "Physical Sciences"}}, {"id": "https://openalex.org/T10824", "display_name": "Image Retrieval and Classification Techniques", "score": 0.987500011920929, "subfield": {"id": "https://openalex.org/subfields/1707", "display_name": "Computer Vision and Pattern Recognition"}, "field": {"id": "https://openalex.org/fields/17", "display_name": "Computer Science"}, "domain": {"id": "https://openalex.org/domains/3", "display_name": "Physical Sciences"}}], "keywords": [{"id": "https://openalex.org/keywords/clutter", "display_name": "Clutter", "score": 0.7268499135971069}, {"id": "https://openalex.org/keywords/computer-science", "display_name": "Computer science", "score": 0.6814479827880859}, {"id": "https://openalex.org/keywords/dimension", "display_name": "Dimension (graph theory)", "score": 0.6312298774719238}, {"id": "https://openalex.org/keywords/reduction", "display_name": "Reduction (mathematics)", "score": 0.61253422498703}, {"id": "https://openalex.org/keywords/visualization", "display_name": "Visualization", "score": 0.6024613380432129}, {"id": "https://openalex.org/keywords/dimensionality-reduction", "display_name": "Dimensionality reduction", "score": 0.5760306119918823}, {"id": "https://openalex.org/keywords/data-visualization", "display_name": "Data visualization", "score": 0.4971180260181427}, {"id": "https://openalex.org/keywords/data-reduction", "display_name": "Data reduction", "score": 0.41579532623291016}, {"id": "https://openalex.org/keywords/algorithm", "display_name": "Algorithm", "score": 0.35203099250793457}, {"id": "https://openalex.org/keywords/artificial-intelligence", "display_name": "Artificial intelligence", "score": 0.33550795912742615}, {"id": "https://openalex.org/keywords/data-mining", "display_name": "Data mining", "score": 0.1672716736793518}, {"id": "https://openalex.org/keywords/mathematics", "display_name": "Mathematics", "score": 0.15400409698486328}, {"id": "https://openalex.org/keywords/geometry", "display_name": "Geometry", "score": 0.09285968542098999}, {"id": "https://openalex.org/keywords/radar", "display_name": "Radar", "score": 0.08239918947219849}], "concepts": [{"id": "https://openalex.org/C132094186", "wikidata": "https://www.wikidata.org/wiki/Q641585", "display_name": "Clutter", "level": 3, "score": 0.7268499135971069}, {"id": "https://openalex.org/C41008148", "wikidata": "https://www.wikidata.org/wiki/Q21198", "display_name": "Computer science", "level": 0, "score": 0.6814479827880859}, {"id": "https://openalex.org/C33676613", "wikidata": "https://www.wikidata.org/wiki/Q13415176", "display_name": "Dimension (graph theory)", "level": 2, "score": 0.6312298774719238}, {"id": "https://openalex.org/C111335779", "wikidata": "https://www.wikidata.org/wiki/Q3454686", "display_name": "Reduction (mathematics)", "level": 2, "score": 0.61253422498703}, {"id": "https://openalex.org/C36464697", "wikidata": "https://www.wikidata.org/wiki/Q451553", "display_name": "Visualization", "level": 2, "score": 0.6024613380432129}, {"id": "https://openalex.org/C70518039", "wikidata": "https://www.wikidata.org/wiki/Q16000077", "display_name": "Dimensionality reduction", "level": 2, "score": 0.5760306119918823}, {"id": "https://openalex.org/C172367668", "wikidata": "https://www.wikidata.org/wiki/Q6504956", "display_name": "Data visualization", "level": 3, "score": 0.4971180260181427}, {"id": "https://openalex.org/C153914771", "wikidata": "https://www.wikidata.org/wiki/Q5227343", "display_name": "Data reduction", "level": 2, "score": 0.41579532623291016}, {"id": "https://openalex.org/C11413529", "wikidata": "https://www.wikidata.org/wiki/Q8366", "display_name": "Algorithm", "level": 1, "score": 0.35203099250793457}, {"id": "https://openalex.org/C154945302", "wikidata": "https://www.wikidata.org/wiki/Q11660", "display_name": "Artificial intelligence", "level": 1, "score": 0.33550795912742615}, {"id": "https://openalex.org/C124101348", "wikidata": "https://www.wikidata.org/wiki/Q172491", "display_name": "Data mining", "level": 1, "score": 0.1672716736793518}, {"id": "https://openalex.org/C33923547", "wikidata": "https://www.wikidata.org/wiki/Q395", "display_name": "Mathematics", "level": 0, "score": 0.15400409698486328}, {"id": "https://openalex.org/C2524010", "wikidata": "https://www.wikidata.org/wiki/Q8087", "display_name": "Geometry", "level": 1, "score": 0.09285968542098999}, {"id": "https://openalex.org/C554190296", "wikidata": "https://www.wikidata.org/wiki/Q47528", "display_name": "Radar", "level": 2, "score": 0.08239918947219849}, {"id": "https://openalex.org/C202444582", "wikidata": "https://www.wikidata.org/wiki/Q837863", "display_name": "Pure mathematics", "level": 1, "score": 0.0}, {"id": "https://openalex.org/C76155785", "wikidata": "https://www.wikidata.org/wiki/Q418", "display_name": "Telecommunications", "level": 1, "score": 0.0}], "mesh": [], "locations_count": 1, "locations": [{"id": "doi:10.1109/infvis.2004.15", "is_oa": false, "landing_page_url": "https://doi.org/10.1109/infvis.2004.15", "pdf_url": null, "source": {"id": "https://openalex.org/S4306418832", "display_name": "IEEE Symposium on Information Visualization", "issn_l": null, "issn": null, "is_oa": false, "is_in_doaj": false, "is_core": false, "host_organization": null, "host_organization_name": null, "host_organization_lineage": [], "host_organization_lineage_names": [], "type": "conference"}, "license": null, "license_id": null, "version": "publishedVersion", "is_accepted": true, "is_published": true, "raw_source_name": "IEEE Symposium on Information Visualization", "raw_type": "proceedings-article"}], "best_oa_location": null, "sustainable_development_goals": [], "awards": [], "funders": [], "has_content": {"grobid_xml": false, "pdf": false}, "referenced_works_count": 26, "referenced_works": ["https://openalex.org/W1493815292", "https://openalex.org/W2160382748", "https://openalex.org/W1651915441", "https://openalex.org/W4250305371", "https://openalex.org/W2166828145", "https://openalex.org/W6647794503", "https://openalex.org/W4246354968", "https://openalex.org/W1976160686", "https://openalex.org/W6635738559", "https://openalex.org/W4241481750", "https://openalex.org/W2017390502", "https://openalex.org/W6644352162", "https://openalex.org/W6677063681", "https://openalex.org/W1613201427", "https://openalex.org/W4235948177", "https://openalex.org/W2064751934", "https://openalex.org/W4245245049", "https://openalex.org/W2104387755", "https://openalex.org/W4292023222", "https://openalex.org/W2047046780", "https://openalex.org/W1597579683", "https://openalex.org/W4242123375", "https://openalex.org/W1823329909", "https://openalex.org/W2114005694", "https://openalex.org/W2752885492", "https://openalex.org/W1977050089"], "related_works": ["https://openalex.org/W2013728941", "https://openalex.org/W4225274103", "https://openalex.org/W2154046714", "https://openalex.org/W2189613078", "https://openalex.org/W2579659702", "https://openalex.org/W2923661510", "https://openalex.org/W1574055964", "https://openalex.org/W1965329638", "https://openalex.org/W2542318691", "https://openalex.org/W3160708108"], "abstract_inverted_index": {"Visual": [0], "clutter": [1, 26, 46, 95, 135, 149, 162], "denotes": [2], "a": [3, 23, 79, 88, 110, 118, 144, 164], "disordered": [4], "collection": [5], "of": [6, 50, 59, 66, 138], "graphical": [7], "entities": [8], "in": [9, 18, 22, 87, 104, 136, 150, 163], "information": [10, 98], "visualization.": [11], "Clutter": [12, 107], "can": [13, 27, 76], "obscure": [14], "the": [15, 19, 32, 51, 56, 60, 64, 84, 102, 161], "structure": [16], "present": [17, 63], "data.": [20], "Even": [21], "small": [24], "dataset,": [25], "make": [28], "it": [29, 90], "hard": [30], "for": [31, 121, 156], "viewer": [33], "to": [34, 93, 146], "find": [35], "patterns,": [36], "relationships": [37], "and": [38, 62], "structure.": [39], "In": [40, 113], "this": [41, 114, 151], "paper,": [42, 115], "we": [43, 116, 131, 142, 154], "define": [44], "visual": [45, 148], "as": [47], "any": [48, 105], "aspect": [49], "visualization": [52, 124], "that": [53, 75, 159], "interferes": [54], "with": [55], "viewer's": [57], "understanding": [58], "data,": [61], "concept": [65], "clutter-based": [67], "dimension": [68, 85], "reordering.": [69], "Dimension": [70], "order": [71, 86, 158], "is": [72, 91, 109], "an": [73, 157], "attribute": [74], "significantly": [77], "affect": [78], "visualization's": [80], "expressiveness.": [81], "By": [82], "varying": [83], "display,": [89], "possible": [92], "reduce": [94], "without": [96], "reducing": [97], "content": [99], "or": [100], "modifying": [101], "data": [103], "way.": [106], "reduction": [108], "display-dependent": [111], "task.": [112], "follow": [117], "three-step": [119], "procedure": [120], "four": [122], "different": [123], "techniques.": [125], "For": [126], "each": [127], "display": [128, 139], "technique,": [129], "first,": [130], "determine": [132], "what": [133], "constitutes": [134], "terms": [137], "properties;": [140], "then": [141], "design": [143], "metric": [145], "measure": [147], "display;": [152], "finally": [153], "search": [155], "minimizes": [160], "display.": [165]}, "counts_by_year": [{"year": 2025, "cited_by_count": 3}, {"year": 2024, "cited_by_count": 5}, {"year": 2023, "cited_by_count": 8}, {"year": 2022, "cited_by_count": 9}, {"year": 2021, "cited_by_count": 4}, {"year": 2020, "cited_by_count": 5}, {"year": 2019, "cited_by_count": 8}, {"year": 2018, "cited_by_count": 12}, {"year": 2017, "cited_by_count": 4}, {"year": 2016, "cited_by_count": 10}, {"year": 2015, "cited_by_count": 14}, {"year": 2014, "cited_by_count": 12}, {"year": 2013, "cited_by_count": 14}, {"year": 2012, "cited_by_count": 15}], "updated_date": "2025-11-06T03:46:38.306776", "created_date": "2025-10-10T00:00:00"}